shocktubecalc/__init__.py
shocktubecalc/sod.py
shocktubecalc-0.14.dist-info/DESCRIPTION.rst
shocktubecalc-0.14.dist-info/METADATA
shocktubecalc-0.14.dist-info/RECORD
shocktubecalc-0.14.dist-info/WHEEL
shocktubecalc-0.14.dist-info/metadata.json
shocktubecalc-0.14.dist-info/top_level.txt
